secsend_webapp/__init__.py
secsend_webapp/__version__.py
secsend_webapp/root/2b499f2097ab84158022.svg
secsend_webapp/root/5c6d0c0d82f2992ebb11.svg
secsend_webapp/root/dl.858ab078b4538a5ab311.js
secsend_webapp/root/dl.b92a521b8fc7a971b529.css
secsend_webapp/root/dl.html
secsend_webapp/root/index.html
secsend_webapp/root/main.17c7c3a3b372ba335c18.css
secsend_webapp/root/main.6d8072eb1f0d3a91f959.js
secsend_webapp/root/sw.js
secsend_webapp-1.1.1.dist-info/METADATA
secsend_webapp-1.1.1.dist-info/WHEEL
secsend_webapp-1.1.1.dist-info/top_level.txt
secsend_webapp-1.1.1.dist-info/RECORD
