Metadata-Version: 2.1
Name: secsend-webapp
Version: 1.1.1
Summary: secsend webapp static files
Home-page: http://github.com/aguinet/secsend
Author: Adrien Guinet
Author-email: adrien@guinet.me
License: GPL
